dataconvertor/__init__.py
dataconvertor/convertor.py
dataconvertor-0.0.1.dist-info/METADATA
dataconvertor-0.0.1.dist-info/WHEEL
dataconvertor-0.0.1.dist-info/top_level.txt
dataconvertor-0.0.1.dist-info/RECORD
