Metadata-Version: 2.1
Name: dataconvertor
Version: 0.0.1
Summary: This is the simplest module for quick work with data.
Home-page: https://github.com/penvoy/lib_dataconvertor.git
Author: penvoy
Author-email: zcmll356@gmail.com
Project-URL: GitHub, https://github.com/penvoy/lib_dataconvertor.git
Keywords: files speedfiles
Classifier: Programming Language :: Python :: 3.11
Classifier: License :: OSI Approved :: MIT License
Classifier: Operating System :: OS Independent
Requires-Python: >=3.6
Requires-Dist: requests >=2.25.1
